jupyterdartkernel/__init__.py
jupyterdartkernel/__main__.py
jupyterdartkernel/install_kernelspec.py
jupyterdartkernel/kernel.py
jupyterdartkernel-0.1.1.dist-info/METADATA
jupyterdartkernel-0.1.1.dist-info/WHEEL
jupyterdartkernel-0.1.1.dist-info/top_level.txt
jupyterdartkernel-0.1.1.dist-info/RECORD
