Metadata-Version: 2.1
Name: jupyterdartkernel
Version: 0.1.1
Summary: package_description
Project-URL: repo, https://github.com/moveread/REPO.git
Requires-Python: >=3.10
